lsvine/__init__.py
lsvine/cli.py
lsvine-0.1.3.dist-info/LICENSE
lsvine-0.1.3.dist-info/METADATA
lsvine-0.1.3.dist-info/WHEEL
lsvine-0.1.3.dist-info/entry_points.txt
lsvine-0.1.3.dist-info/top_level.txt
lsvine-0.1.3.dist-info/RECORD
