Metadata-Version: 2.1
Name: lsvine
Version: 0.1.3
Summary: List contents of directories in a vine-like format.
Home-page: https://github.com/autofitcloud/lsvine
Author: Shadi Akiki, AutofitCloud
Author-email: shadi@autofitcloud.com
License: UNKNOWN
Platform: UNKNOWN
Requires-Dist: click (==7.0)
Requires-Dist: pandas (==0.25.3)
Requires-Dist: tabulate (==0.8.6)
Requires-Dist: termcolor (==1.1.0)
